README.md
setup.py
aschot_pulumi_dbtcloud/__init__.py
aschot_pulumi_dbtcloud/_inputs.py
aschot_pulumi_dbtcloud/_utilities.py
aschot_pulumi_dbtcloud/big_query_connection.py
aschot_pulumi_dbtcloud/big_query_credential.py
aschot_pulumi_dbtcloud/connection.py
aschot_pulumi_dbtcloud/databricks_credential.py
aschot_pulumi_dbtcloud/environment.py
aschot_pulumi_dbtcloud/environment_variable.py
aschot_pulumi_dbtcloud/environment_variable_job_override.py
aschot_pulumi_dbtcloud/extended_attributes.py
aschot_pulumi_dbtcloud/fabric_connection.py
aschot_pulumi_dbtcloud/fabric_credential.py
aschot_pulumi_dbtcloud/get_azure_dev_ops_project.py
aschot_pulumi_dbtcloud/get_azure_dev_ops_repository.py
aschot_pulumi_dbtcloud/get_big_query_connection.py
aschot_pulumi_dbtcloud/get_big_query_credential.py
aschot_pulumi_dbtcloud/get_connection.py
aschot_pulumi_dbtcloud/get_databricks_credential.py
aschot_pulumi_dbtcloud/get_environment.py
aschot_pulumi_dbtcloud/get_environment_variable.py
aschot_pulumi_dbtcloud/get_extended_attributes.py
aschot_pulumi_dbtcloud/get_group.py
aschot_pulumi_dbtcloud/get_group_users.py
aschot_pulumi_dbtcloud/get_job.py
aschot_pulumi_dbtcloud/get_notification.py
aschot_pulumi_dbtcloud/get_postgres_credential.py
aschot_pulumi_dbtcloud/get_privatelink_endpoint.py
aschot_pulumi_dbtcloud/get_project.py
aschot_pulumi_dbtcloud/get_repository.py
aschot_pulumi_dbtcloud/get_service_token.py
aschot_pulumi_dbtcloud/get_snowflake_credential.py
aschot_pulumi_dbtcloud/get_user.py
aschot_pulumi_dbtcloud/get_user_groups.py
aschot_pulumi_dbtcloud/get_webhook.py
aschot_pulumi_dbtcloud/group.py
aschot_pulumi_dbtcloud/job.py
aschot_pulumi_dbtcloud/legacy_bigquery_connection.py
aschot_pulumi_dbtcloud/legacy_bigquery_credential.py
aschot_pulumi_dbtcloud/legacy_connection.py
aschot_pulumi_dbtcloud/legacy_databricks_credential.py
aschot_pulumi_dbtcloud/legacy_environment.py
aschot_pulumi_dbtcloud/legacy_environment_variable.py
aschot_pulumi_dbtcloud/legacy_get_big_query_connection.py
aschot_pulumi_dbtcloud.egg-info/PKG-INFO
aschot_pulumi_dbtcloud.egg-info/SOURCES.txt
aschot_pulumi_dbtcloud.egg-info/dependency_links.txt
aschot_pulumi_dbtcloud.egg-info/not-zip-safe
aschot_pulumi_dbtcloud.egg-info/requires.txt
aschot_pulumi_dbtcloud.egg-info/top_level.txt
