Metadata-Version: 2.1
Name: aschot-pulumi-dbtcloud
Version: 0.0.3
Summary: A Pulumi package for creating and managing dbt Cloud resources.
Home-page: https://www.pulumi.com
License: Apache-2.0
Project-URL: Repository, https://github.com/a-schot/pulumi-dbtcloud
Keywords: pulumi dbtcloud dbt cloud category/cloud
Platform: UNKNOWN
Requires-Python: >=3.8
